{
  "seed": 0,
  "modulus": 113,
  "train_fraction": 0.3,
  "d_model": 2048,
  "n_heads": 128,
  "d_head": 16,
  "d_mlp": 8192,
  "n_layers": 8,
  "learning_rate": 0.001,
  "weight_decay": 0.1,
  "adam_beta1": 0.9,
  "adam_beta2": 0.95,
  "adam_eps": 0.1,
  "epochs": 40000,
  "log_every": 100,
  "checkpoint_every": 1000,
  "out_dir": "runs/circuit_sparse_mainline",
  "device": "cuda",
  "causal": true,
  "activation_type": "gelu",
  "rms_norm": true,
  "use_pos_embed": false,
  "attention_sink": false,
  "bigram_table": true,
  "weight_keep_fraction": 0.015625,
  "initial_weight_keep_fraction": 1.0,
  "anneal_weight_sparsity": true,
  "anneal_start_frac": 0.0,
  "anneal_stop_frac": 0.5,
  "schedule_lr_with_l0": true,
  "include_bias_in_weight_sparsity": true,
  "minimum_alive_per_row": 4,
  "activation_keep_fraction": 0.25,
  "activation_sparsity_locations": "attn_in,attn_q,attn_k,attn_v,attn_out,mlp_in,mlp_neuron,mlp_out,resid_post_attn,resid_post_mlp",
  "lr_warmup_frac": 0.01,
  "lr_decay": true,
  "grad_clip_rms": 1.0
}
